tests
xgbtune
