Metadata-Version: 1.2
Name: xgbtune
Version: 1.0.1
Summary: Automated XGBoost tunning
Home-page: https://github.com/MainRo/xgbtune.git
Author: Romain Picard
Author-email: romain.picard@oakbits.com
License: MIT
Project-URL: Documentation, https://xgbtune.readthedocs.io
Platform: any
Classifier: Development Status :: 5 - Production/Stable
Classifier: License :: OSI Approved :: MIT License
Classifier: Intended Audience :: Developers
Classifier: Programming Language :: Python :: 3
Classifier: Topic :: Scientific/Engineering :: Artificial Intelligence
